quantum_gates/__init__.py
quantum_gates/backends.py
quantum_gates/circuits.py
quantum_gates/factories.py
quantum_gates/gates.py
quantum_gates/integrators.py
quantum_gates/metrics.py
quantum_gates/pulses.py
quantum_gates/qiskit_provider.py
quantum_gates/quantum_algorithms.py
quantum_gates/simulators.py
quantum_gates/utilities.py
quantum_gates/_gates/__init__.py
quantum_gates/_gates/factories.py
quantum_gates/_gates/gates.py
quantum_gates/_gates/integrator.py
quantum_gates/_gates/pulse.py
quantum_gates/_legacy/__init__.py
quantum_gates/_legacy/circuit.py
quantum_gates/_legacy/gates.py
quantum_gates/_legacy/simulator.py
quantum_gates/_qiskit_provider/__init__.py
quantum_gates/_qiskit_provider/ng_backend.py
quantum_gates/_qiskit_provider/ng_job.py
quantum_gates/_qiskit_provider/ng_provider.py
quantum_gates/_simulation/__init__.py
quantum_gates/_simulation/backend.py
quantum_gates/_simulation/circuit.py
quantum_gates/_simulation/simulator.py
quantum_gates/_utility/__init__.py
quantum_gates/_utility/circ_optimizer.py
quantum_gates/_utility/device_parameters.py
quantum_gates/_utility/quantum_algorithms.py
quantum_gates/_utility/simulations_utility.py
quantum_gates-2.3.0.dist-info/licenses/LICENSE
quantum_gates-2.3.0.dist-info/METADATA
quantum_gates-2.3.0.dist-info/WHEEL
quantum_gates-2.3.0.dist-info/top_level.txt
quantum_gates-2.3.0.dist-info/RECORD
