Metadata-Version: 2.4
Name: quantum-gates
Version: 2.3.0
Summary: Quantum Noisy Gates Simulation with Python
Home-page: https://github.com/CERN-IT-INNOVATION/quantum-gates/
Author: M. Grossi, G. D. Bartolomeo, M. Vischi, P. Da Rold, R. Wixinger
Author-email: "M, Grossi" <michele.grossi@cern.ch>, "G. D. Bartolomeo" <dibartolomeo.giov@gmail.com>, "M. Vischi" <vischimichele@gmail.com>, "P. Da Rold" <PAOLO.DAROLD@studenti.units.it>, "R. Wixinger" <roman.wixinger@gmail.com>
License: MIT
Classifier: Programming Language :: Python :: 3
Classifier: License :: OSI Approved :: MIT License
Classifier: Operating System :: Unix
Classifier: Topic :: Scientific/Engineering :: Mathematics
Requires-Python: >=3.9
License-File: LICENSE
Requires-Dist: numpy>=1.22
Requires-Dist: qiskit-aer>=0.17.0
Requires-Dist: qiskit>=2.0
Requires-Dist: qiskit-ibm-runtime>=0.39.0
Requires-Dist: scipy
Requires-Dist: matplotlib
Requires-Dist: pylatexenc
Requires-Dist: opt-einsum
Requires-Dist: pytest
Requires-Dist: pylint
Requires-Dist: python-dotenv
Requires-Dist: build
Provides-Extra: demo
Requires-Dist: jupyter; extra == "demo"
Provides-Extra: docs
Requires-Dist: sphinx>=4.5.0; extra == "docs"
Requires-Dist: sphinx-rtd-theme>=1.0.0; extra == "docs"
Requires-Dist: sphinxcontrib-napoleon>=0.7; extra == "docs"
Requires-Dist: sphinx-autoapi>=2.0.1; extra == "docs"
Dynamic: author
Dynamic: license
Dynamic: license-file
Dynamic: requires-python
